pyIPRoyalPawns/__init__.py
pyIPRoyalPawns/exceptions.py
pyIPRoyalPawns/ipr.py
pyIPRoyalPawns-1.1.5.dist-info/LICENSE
pyIPRoyalPawns-1.1.5.dist-info/METADATA
pyIPRoyalPawns-1.1.5.dist-info/WHEEL
pyIPRoyalPawns-1.1.5.dist-info/top_level.txt
pyIPRoyalPawns-1.1.5.dist-info/RECORD
