Metadata-Version: 2.1
Name: pyIPRoyalPawns
Version: 1.1.5
Summary: UNOFFICIAL Python bindings for IPRoyal Pawns (Pawns.app) Dashboard API
Home-page: https://github.com/coder-amogh/pyIPRoyalPawns
Author: coder-amogh (Amogh Datar)
License: UNKNOWN
Project-URL: Bug Tracker, https://github.com/coder-amogh/pyIPRoyalPawns/issues
Keywords: python,iproyal,ipr,passive income,iproyal pawns api,iproyal pawns dashboard,python iproyal pawns,pawns.app
Platform: UNKNOWN
Classifier: Development Status :: 5 - Production/Stable
Classifier: Intended Audience :: Developers
Classifier: Programming Language :: Python :: 3
Classifier: Operating System :: OS Independent
License-File: LICENSE
Requires-Dist: requests
Requires-Dist: pySocks
